boodle/__init__.py
boodle/agent.py
boodle/builtin.py
boodle/cboodle_stdout.cpython-37m-darwin.so
boodle/exceptions.py
boodle/generator.py
boodle/listen.py
boodle/music.py
boodle/sample.py
boodle/stereo.py
boodle/test_stereo.py
boodle/utilities.py
boodler_redux-3.0.0.data/scripts/boodle-event
boodler_redux-3.0.0.data/scripts/boodle-mgr
boodler_redux-3.0.0.data/scripts/boodler
booman/__init__.py
booman/command.py
booman/create.py
booman/exceptions.py
booman/frame.py
booman/test_create.py
booman/token.py
boopak/__init__.py
boopak/argdef.py
boopak/collect.py
boopak/emptymodule.py
boopak/exceptions.py
boopak/fetch.py
boopak/package.py
boopak/pinfo.py
boopak/pload.py
boopak/sparse.py
boopak/test_argdef.py
boopak/test_pinfo.py
boopak/test_pload.py
boopak/test_sparse.py
boodler_redux-3.0.0.dist-info/METADATA
boodler_redux-3.0.0.dist-info/WHEEL
boodler_redux-3.0.0.dist-info/top_level.txt
boodler_redux-3.0.0.dist-info/RECORD
