Metadata-Version: 2.1
Name: boodler-redux
Version: 3.0.0
Summary: A programmable soundscape tool
Home-page: https://github.com/beaugunderson/boodler-redux
Author: Beau Gunderson
Author-email: beau@beaugunderson.com
License: GNU LGPL
Platform: MacOS X
Platform: POSIX
Classifier: Topic :: Multimedia :: Sound/Audio :: Mixers
Classifier: Development Status :: 5 - Production/Stable
Classifier: Environment :: Console
Classifier: Intended Audience :: End Users/Desktop
Classifier: License :: OSI Approved :: GNU Library or Lesser General Public License (LGPL)
Classifier: Operating System :: POSIX
Classifier: Operating System :: MacOS :: MacOS X
Classifier: Programming Language :: Python :: 3
Requires-Dist: packaging
